package/__init__.py
package/bake_libs.sh
package/wrapper.py
package/bin/file
package/bin/rosbag
package/include/pointcloudmodifier.hpp
package/lib/libaction_msgs__rosidl_generator_c.so
package/lib/libaction_msgs__rosidl_typesupport_c.so
package/lib/libaction_msgs__rosidl_typesupport_cpp.so
package/lib/libaction_msgs__rosidl_typesupport_fastrtps_c.so
package/lib/libaction_msgs__rosidl_typesupport_fastrtps_cpp.so
package/lib/libaction_msgs__rosidl_typesupport_introspection_c.so
package/lib/libaction_msgs__rosidl_typesupport_introspection_cpp.so
package/lib/libament_index_cpp.so
package/lib/libbuiltin_interfaces__rosidl_generator_c.so
package/lib/libbuiltin_interfaces__rosidl_typesupport_c.so
package/lib/libbuiltin_interfaces__rosidl_typesupport_cpp.so
package/lib/libbuiltin_interfaces__rosidl_typesupport_fastrtps_c.so
package/lib/libbuiltin_interfaces__rosidl_typesupport_fastrtps_cpp.so
package/lib/libbuiltin_interfaces__rosidl_typesupport_introspection_c.so
package/lib/libbuiltin_interfaces__rosidl_typesupport_introspection_cpp.so
package/lib/libfastcdr.so
package/lib/libfastcdr.so.1
package/lib/libfastcdr.so.1.0.29
package/lib/libfastrtps.so
package/lib/libfastrtps.so.2.6
package/lib/libfastrtps.so.2.6.11
package/lib/libgeometry_msgs__rosidl_generator_c.so
package/lib/libgeometry_msgs__rosidl_typesupport_c.so
package/lib/libgeometry_msgs__rosidl_typesupport_cpp.so
package/lib/libgeometry_msgs__rosidl_typesupport_fastrtps_c.so
package/lib/libgeometry_msgs__rosidl_typesupport_fastrtps_cpp.so
package/lib/libgeometry_msgs__rosidl_typesupport_introspection_c.so
package/lib/libgeometry_msgs__rosidl_typesupport_introspection_cpp.so
package/lib/libpcl_msgs__rosidl_generator_c.so
package/lib/libpcl_msgs__rosidl_typesupport_c.so
package/lib/libpcl_msgs__rosidl_typesupport_cpp.so
package/lib/libpcl_msgs__rosidl_typesupport_fastrtps_c.so
package/lib/libpcl_msgs__rosidl_typesupport_fastrtps_cpp.so
pointcloudcrafter-1.2.4.dist-info/METADATA
pointcloudcrafter-1.2.4.dist-info/WHEEL
pointcloudcrafter-1.2.4.dist-info/entry_points.txt
pointcloudcrafter-1.2.4.dist-info/RECORD
pointcloudcrafter-1.2.4.dist-info/licenses/LICENSE
pointcloudcrafter-1.2.4.dist-info/sboms/auditwheel.cdx.json
