Metadata-Version: 2.2
Name: pointcloudcrafter
Version: 1.2.4
Summary: Tools for Handling, Manipulating and Analyzing of Point Clouds
Keywords: point cloud,LiDAR,C++,ROS2,PCL
Author-Email: Dominik Kulmer <dominik.kulmer@tum.de>, Maximilian Leitenstern <maxi.leitenstern@tum.de>
Classifier: Intended Audience :: Developers
Classifier: Intended Audience :: Education
Classifier: Intended Audience :: Other Audience
Classifier: Intended Audience :: Science/Research
Classifier: License :: OSI Approved :: Apache Software License
Classifier: Operating System :: POSIX :: Linux
Classifier: Programming Language :: C++
Project-URL: Homepage, https://github.com/TUMFTM/PointCloudCrafter
Requires-Python: >=3.10
